{
    "gameTime": 600.0,
    "goalsData": [
        {
            "goalScorerName": "Amman",
            "goalShotTime": 99.1,
            "goalSide": "Blue",
            "goalTime": 100.717,
            "goalTravelTime": 1.617
        },
        {
            "goalScorerName": "Amman",
            "goalShotTime": 172.7,
            "goalSide": "Blue",
            "goalTime": 174.167,
            "goalTravelTime": 1.467
        },
        {
            "goalScorerName": "MaddoHatto",
            "goalShotTime": 346.3,
            "goalSide": "Red",
            "goalTime": 346.383,
            "goalTravelTime": 0.083
        },
        {
            "goalScorerName": "MaddoHatto",
            "goalShotTime": 389.167,
            "goalSide": "Red",
            "goalTime": 390.317,
            "goalTravelTime": 1.15
        },
        {
            "goalScorerName": "Amman",
            "goalShotTime": 446.633,
            "goalSide": "Blue",
            "goalTime": 447.817,
            "goalTravelTime": 1.184
        },
        {
            "goalScorerName": "Amman",
            "goalShotTime": 599.4,
            "goalSide": "Blue",
            "goalTime": 600.017,
            "goalTravelTime": 0.617
        }
    ],
    "rawPositionsAtEnd": "-89.5291353939799--117.4602274577475|151.17240718467895-14.519934021377237|-109.16658706389862--84.39084139025785|26.98388494235672--41.888927683866704|",
    "score": {
        "Blue": 3,
        "Red": 2
    },
    "teams": {
        "Blue": [
            "Amman",
            "adamaru"
        ],
        "Red": [
            "MaddoHatto",
            "ToPP"
        ]
    },
    "time": "2020-08-11 09:13"
}